LICENSE.txt
README.md
setup.cfg
setup.py
datalibro_backend/__init__.py
datalibro_backend/config.py
datalibro_backend/data_sync.py
datalibro_backend/openmetadata_pipeline_manager.py
datalibro_backend/quality_check.py
datalibro_backend/read_file.py
datalibro_backend.egg-info/PKG-INFO
datalibro_backend.egg-info/SOURCES.txt
datalibro_backend.egg-info/dependency_links.txt
datalibro_backend.egg-info/requires.txt
datalibro_backend.egg-info/top_level.txt