Metadata-Version: 2.1
Name: datalibro_backend
Version: 1.2.24
Summary: A small package for your backend service
Author: lucy
Author-email: lucy@petlibro.com
Classifier: Programming Language :: Python :: 3
Classifier: License :: OSI Approved :: MIT License
Classifier: Operating System :: OS Independent
License-File: LICENSE.txt
Requires-Dist: pymysql
Requires-Dist: pandas
Requires-Dist: pyyaml
